Day_006/d_ff.v
module D_FF(clk,rst,D_in,D_out);
input D_in;
input clk,rst;
output reg D_out;

always@(posedge clk) begin
if(rst) begin
D_out<=1'b0;
end
else begin
D_out<=D_in;
end
end


endmodule

Day_006/D_FF_tb.v
module D_FF_tb;

	// Inputs
	reg clk;
	reg rst;
	reg D_in;

	// Outputs
	wire D_out;

	// Instantiate the Unit Under Test (UUT)
	D_FF uut (
		.clk(clk), 
		.rst(rst), 
		.D_in(D_in), 
		.D_out(D_out)
	);

	initial begin
		// Initialize Inputs
		$dumpfile("d_ff.vcd");
		$dumpvars(0,D_FF_tb);
        $monitor($time,"rst=%b,D_in=%b, D_out=%b",rst,D_in,D_out);

		clk = 0;
		rst = 0;
		D_in = 0;

		
		#10;
		rst = 0;
		D_in = 1;
		
		#13;
		rst = 1;
		D_in = 1;

      
		#5;
		rst = 0;
		D_in = 0;



      #25;
		rst = 0;
		D_in = 1;

      #10;
		rst = 1;
		D_in = 1;
		
		#14
		$stop;



	end
   always #5 clk=~clk;   
endmodule

Day_006/d_ff.vcd
$date
	Tue Aug 29 21:27:46 2023
$end
$version
	Icarus Verilog
$end
$timescale
	1s
$end
$scope module D_FF_tb $end
$var wire 1 ! D_out $end
$var reg 1 " D_in $end
$var reg 1 # clk $end
$var reg 1 $ rst $end
$scope module uut $end
$var wire 1 " D_in $end
$var wire 1 # clk $end
$var wire 1 $ rst $end
$var reg 1 ! D_out $end
$upscope $end
$upscope $end
$enddefinitions $end
$comment Show the parameter values. $end
$dumpall
$end
#0
$dumpvars
0$
0#
0"
x!
$end
#5
0!
1#
#10
0#
1"
#15
1!
1#
#20
0#
#23
1$
#25
0!
1#
#28
0"
0$
#30
0#
#35
1#
#40
0#
#45
1#
#50
0#
#53
1"
#55
1!
1#
#60
0#
#63
1$
#65
0!
1#
