Day_008/T_ff.v
module T_ff(clk,rst,T_in,T_out);

input clk,rst;
input T_in;
output T_out;
wire temp;
assign temp=~T_in;
D_FF d1(clk,rst,temp,T_out);

endmodule

module D_FF(clk,rst,D_in,D_out);
input D_in;
input clk,rst;
output reg D_out;
always@(posedge clk) begin
if(rst) begin
D_out<=1'b0;
end
else begin
D_out<=D_in;
end
end
endmodule

Day_008/T_ff_tb.v
module T_ff_tb;
	reg clk;
	reg rst;
	reg T_in;
	wire T_out;
	T_ff uut (
		.clk(clk), 
		.rst(rst), 
		.T_in(T_in), 
		.T_out(T_out)
	);

	initial begin
		$dumpfile("t_ff.vcd");
		$dumpvars(0,T_ff_tb);
        $monitor($time," rst=%b, T_in=%b, T_out=%b",rst,T_in,T_out);
		clk = 0;
		rst = 0;
		T_in = 0;

		#10;
		rst = 0;
		T_in = 1;
		
		#13;
		rst = 1;
		T_in = 1;

		#5;
		rst = 0;
		T_in = 0;

      #25;
		rst = 0;
		T_in = 1;

      #10;
		rst = 1;
		T_in = 1;
		
		#14
		$stop;

	end
     always #5 clk=~clk; 
endmodule

Day_008/t_ff.vcd
$date
	Thu Aug 31 23:12:01 2023
$end
$version
	Icarus Verilog
$end
$timescale
	1s
$end
$scope module T_ff_tb $end
$var wire 1 ! T_out $end
$var reg 1 " T_in $end
$var reg 1 # clk $end
$var reg 1 $ rst $end
$scope module uut $end
$var wire 1 " T_in $end
$var wire 1 # clk $end
$var wire 1 $ rst $end
$var wire 1 % temp $end
$var wire 1 ! T_out $end
$scope module d1 $end
$var wire 1 % D_in $end
$var wire 1 # clk $end
$var wire 1 $ rst $end
$var reg 1 ! D_out $end
$upscope $end
$upscope $end
$upscope $end
$enddefinitions $end
$comment Show the parameter values. $end
$dumpall
$end
#0
$dumpvars
1%
0$
0#
0"
x!
$end
#5
1!
1#
#10
0%
0#
1"
#15
0!
1#
#20
0#
#23
1$
#25
1#
#28
1%
0"
0$
#30
0#
#35
1!
1#
#40
0#
#45
1#
#50
0#
#53
0%
1"
#55
0!
1#
#60
0#
#63
1$
