Day_016/ram_rd.v
// Single port parameterized RAM with asynchronous read/write without bidirectional inout datatype
module ram_rd(data_out, data_in, addr, wr, cs);
    parameter addr_size=10, word_size=8, mem_size=1024;
    input [addr_size-1:0] addr;
    input [word_size-1:0] data_in;
    input wr,cs;
    output [word_size-1:0] data_out;
    reg [word_size-1:0] mem [mem_size-1:0];
    assign data_out = mem[addr];
    always @(wr or cs) 
        if (wr)
            mem[addr]=data_in;
endmodule

Day_016/ram_tb.v
module ram_tb;
reg [9:0] address;
wire [7:0] data_out;
reg [7:0] data_in;
reg write, select;
integer k, myseed;
ram_rd RAM (data_out, data_in, address, write, select);
initial
begin
$dumpfile("ram.vcd");
$dumpvars(0,ram_tb);
for (k=0; k<=1023; k=k+1)
begin
address = k;
data_in = (k + k) % 256; write = 1; select = 1;
#2 write = 0; select = 0;
end
repeat (20)
begin
#2 address = $random(myseed) % 1024; write = 0; select = 1;
$display("Address: %5d, Data: %4d", address,data_out);
#2 select = 0;
end
end
initial myseed =35;
endmodule

Day_016/ram.vcd
$date
	Mon Sep 18 13:59:30 2023
$end
$version
	Icarus Verilog
$end
$timescale
	1s
$end
$scope module ram_tb $end
$var wire 8 ! data_out [7:0] $end
$var reg 10 " address [9:0] $end
$var reg 8 # data_in [7:0] $end
$var reg 1 $ select $end
$var reg 1 % write $end
$var integer 32 & k [31:0] $end
$var integer 32 ' myseed [31:0] $end
$scope module RAM $end
$var wire 10 ( addr [9:0] $end
$var wire 1 $ cs $end
$var wire 8 ) data_in [7:0] $end
$var wire 8 * data_out [7:0] $end
$var wire 1 % wr $end
$var parameter 32 + addr_size $end
$var parameter 32 , mem_size $end
$var parameter 32 - word_size $end
$upscope $end
$upscope $end
$enddefinitions $end
$comment Show the parameter values. $end
$dumpall
b1000 -
b10000000000 ,
b1010 +
$end
#0
$dumpvars
b0 *
b0 )
b0 (
b100011 '
b0 &
1%
1$
b0 #
b0 "
b0 !
$end
#2
b10 #
b10 )
b10 !
b10 *
b1 "
b1 (
b1 &
1$
1%
#4
b100 #
b100 )
b100 !
b100 *
b10 "
b10 (
b10 &
1$
1%
#6
b110 #
b110 )
b110 !
b110 *
b11 "
b11 (
b11 &
1$
1%
#8
b1000 #
b1000 )
b1000 !
b1000 *
b100 "
b100 (
b100 &
1$
1%
#10
b1010 #
b1010 )
b1010 !
b1010 *
b101 "
b101 (
b101 &
1$
1%
#12
b1100 #
b1100 )
b1100 !
b1100 *
b110 "
b110 (
b110 &
1$
1%
#14
b1110 #
b1110 )
b1110 !
b1110 *
b111 "
b111 (
b111 &
1$
1%
#16
b10000 #
b10000 )
b10000 !
b10000 *
b1000 "
b1000 (
b1000 &
1$
1%
#18
b10010 #
b10010 )
b10010 !
b10010 *
b1001 "
b1001 (
b1001 &
1$
1%
#20
b10100 #
b10100 )
b10100 !
b10100 *
b1010 "
b1010 (
b1010 &
1$
1%
#22
b10110 #
b10110 )
b10110 !
b10110 *
b1011 "
b1011 (
b1011 &
1$
1%
#24
b11000 #
b11000 )
b11000 !
b11000 *
b1100 "
b1100 (
b1100 &
1$
1%
#26
b11010 #
b11010 )
b11010 !
b11010 *
b1101 "
b1101 (
b1101 &
1$
1%
#28
b11100 #
b11100 )
b11100 !
b11100 *
b1110 "
b1110 (
b1110 &
1$
1%
#30
b11110 #
b11110 )
b11110 !
b11110 *
b1111 "
b1111 (
b1111 &
1$
1%
#32
b100000 #
b100000 )
b100000 !
b100000 *
b10000 "
b10000 (
b10000 &
1$
1%
#34
b100010 #
b100010 )
b100010 !
b100010 *
b10001 "
b10001 (
b10001 &
1$
1%
#36
b100100 #
b100100 )
b100100 !
b100100 *
b10010 "
b10010 (
b10010 &
1$
1%
#38
b100110 #
b100110 )
b100110 !
b100110 *
b10011 "
b10011 (
b10011 &
1$
1%
#40
b101000 #
b101000 )
b101000 !
b101000 *
b10100 "
b10100 (
b10100 &
1$
1%
#42
b101010 #
b101010 )
b101010 !
b101010 *
b10101 "
b10101 (
b10101 &
1$
1%
#44
b101100 #
b101100 )
b101100 !
b101100 *
b10110 "
b10110 (
b10110 &
1$
1%
#46
b101110 #
b101110 )
b101110 !
b101110 *
b10111 "
b10111 (
b10111 &
1$
1%
#48
b110000 #
b110000 )
b110000 !
b110000 *
b11000 "
b11000 (
b11000 &
1$
1%
#50
b110010 #
b110010 )
b110010 !
b110010 *
b11001 "
b11001 (
b11001 &
1$
1%
#52
b110100 #
b110100 )
b110100 !
b110100 *
b11010 "
b11010 (
b11010 &
1$
1%
#54
b110110 #
b110110 )
b110110 !
b110110 *
b11011 "
b11011 (
b11011 &
1$
1%
#56
b111000 #
b111000 )
b111000 !
b111000 *
b11100 "
b11100 (
b11100 &
1$
1%
#58
b111010 #
b111010 )
b111010 !
b111010 *
b11101 "
b11101 (
b11101 &
1$
1%
#60
b111100 #
b111100 )
b111100 !
b111100 *
b11110 "
b11110 (
b11110 &
1$
1%
#62
b111110 #
b111110 )
b111110 !
b111110 *
b11111 "
b11111 (
b11111 &
1$
1%
#64
b1000000 #
b1000000 )
b1000000 !
b1000000 *
b100000 "
b100000 (
b100000 &
1$
1%
#66
b1000010 #
b1000010 )
b1000010 !
b1000010 *
b100001 "
b100001 (
b100001 &
1$
1%
#68
b1000100 #
b1000100 )
b1000100 !
b1000100 *
b100010 "
b100010 (
b100010 &
1$
1%
#70
b1000110 #
b1000110 )
b1000110 !
b1000110 *
b100011 "
b100011 (
b100011 &
1$
1%
#72
b1001000 #
b1001000 )
b1001000 !
b1001000 *
b100100 "
b100100 (
b100100 &
1$
1%
#74
b1001010 #
b1001010 )
b1001010 !
b1001010 *
b100101 "
b100101 (
b100101 &
1$
1%
#76
b1001100 #
b1001100 )
b1001100 !
b1001100 *
b100110 "
b100110 (
b100110 &
1$
1%
#78
b1001110 #
b1001110 )
b1001110 !
b1001110 *
b100111 "
b100111 (
b100111 &
1$
1%
#80
b1010000 #
b1010000 )
b1010000 !
b1010000 *
b101000 "
b101000 (
b101000 &
1$
1%
#82
b1010010 #
b1010010 )
b1010010 !
b1010010 *
b101001 "
b101001 (
b101001 &
1$
1%
#84
b1010100 #
b1010100 )
b1010100 !
b1010100 *
b101010 "
b101010 (
b101010 &
1$
1%
#86
b1010110 #
b1010110 )
b1010110 !
b1010110 *
b101011 "
b101011 (
b101011 &
1$
1%
#88
b1011000 #
b1011000 )
b1011000 !
b1011000 *
b101100 "
b101100 (
b101100 &
1$
1%
#90
b1011010 #
b1011010 )
b1011010 !
b1011010 *
b101101 "
b101101 (
b101101 &
1$
1%
#92
b1011100 #
b1011100 )
b1011100 !
b1011100 *
b101110 "
b101110 (
b101110 &
1$
1%
#94
b1011110 #
b1011110 )
b1011110 !
b1011110 *
b101111 "
b101111 (
b101111 &
1$
1%
#96
b1100000 #
b1100000 )
b1100000 !
b1100000 *
b110000 "
b110000 (
b110000 &
1$
1%
#98
b1100010 #
b1100010 )
b1100010 !
b1100010 *
b110001 "
b110001 (
b110001 &
1$
1%
#100
b1100100 #
b1100100 )
b1100100 !
b1100100 *
b110010 "
b110010 (
b110010 &
1$
1%
#102
b1100110 #
b1100110 )
b1100110 !
b1100110 *
b110011 "
b110011 (
b110011 &
1$
1%
#104
b1101000 #
b1101000 )
b1101000 !
b1101000 *
b110100 "
b110100 (
b110100 &
1$
1%
#106
b1101010 #
b1101010 )
b1101010 !
b1101010 *
b110101 "
b110101 (
b110101 &
1$
1%
#108
b1101100 #
b1101100 )
b1101100 !
b1101100 *
b110110 "
b110110 (
b110110 &
1$
1%
#110
b1101110 #
b1101110 )
b1101110 !
b1101110 *
b110111 "
b110111 (
b110111 &
1$
1%
#112
b1110000 #
b1110000 )
b1110000 !
b1110000 *
b111000 "
b111000 (
b111000 &
1$
1%
#114
b1110010 #
b1110010 )
b1110010 !
b1110010 *
b111001 "
b111001 (
b111001 &
1$
1%
#116
b1110100 #
b1110100 )
b1110100 !
b1110100 *
b111010 "
b111010 (
b111010 &
1$
1%
#118
b1110110 #
b1110110 )
b1110110 !
b1110110 *
b111011 "
b111011 (
b111011 &
1$
1%
#120
b1111000 #
b1111000 )
b1111000 !
b1111000 *
b111100 "
b111100 (
b111100 &
1$
1%
#122
b1111010 #
b1111010 )
b1111010 !
b1111010 *
b111101 "
b111101 (
b111101 &
1$
1%
#124
b1111100 #
b1111100 )
b1111100 !
b1111100 *
b111110 "
b111110 (
b111110 &
1$
1%
#126
b1111110 #
b1111110 )
b1111110 !
b1111110 *
b111111 "
b111111 (
b111111 &
1$
1%
#128
b10000000 #
b10000000 )
b10000000 !
b10000000 *
b1000000 "
b1000000 (
b1000000 &
1$
1%
#130
b10000010 #
b10000010 )
b10000010 !
b10000010 *
b1000001 "
b1000001 (
b1000001 &
1$
1%
#132
b10000100 #
b10000100 )
b10000100 !
b10000100 *
b1000010 "
b1000010 (
b1000010 &
1$
1%
#134
b10000110 #
b10000110 )
b10000110 !
b10000110 *
b1000011 "
b1000011 (
b1000011 &
1$
1%
#136
b10001000 #
b10001000 )
b10001000 !
b10001000 *
b1000100 "
b1000100 (
b1000100 &
1$
1%
#138
b10001010 #
b10001010 )
b10001010 !
b10001010 *
b1000101 "
b1000101 (
b1000101 &
1$
1%
#140
b10001100 #
b10001100 )
b10001100 !
b10001100 *
b1000110 "
b1000110 (
b1000110 &
1$
1%
#142
b10001110 #
b10001110 )
b10001110 !
b10001110 *
b1000111 "
b1000111 (
b1000111 &
1$
1%
#144
b10010000 #
b10010000 )
b10010000 !
b10010000 *
b1001000 "
b1001000 (
b1001000 &
1$
1%
#146
b10010010 #
b10010010 )
b10010010 !
b10010010 *
b1001001 "
b1001001 (
b1001001 &
1$
1%
#148
b10010100 #
b10010100 )
b10010100 !
b10010100 *
b1001010 "
b1001010 (
b1001010 &
1$
1%
#150
b10010110 #
b10010110 )
b10010110 !
b10010110 *
b1001011 "
b1001011 (
b1001011 &
1$
1%
#152
b10011000 #
b10011000 )
b10011000 !
b10011000 *
b1001100 "
b1001100 (
b1001100 &
1$
1%
#154
b10011010 #
b10011010 )
b10011010 !
b10011010 *
b1001101 "
b1001101 (
b1001101 &
1$
1%
#156
b10011100 #
b10011100 )
b10011100 !
b10011100 *
b1001110 "
b1001110 (
b1001110 &
1$
1%
#158
b10011110 #
b10011110 )
b10011110 !
b10011110 *
b1001111 "
b1001111 (
b1001111 &
1$
1%
#160
b10100000 #
b10100000 )
b10100000 !
b10100000 *
b1010000 "
b1010000 (
b1010000 &
1$
1%
#162
b10100010 #
b10100010 )
b10100010 !
b10100010 *
b1010001 "
b1010001 (
b1010001 &
1$
1%
#164
b10100100 #
b10100100 )
b10100100 !
b10100100 *
b1010010 "
b1010010 (
b1010010 &
1$
1%
#166
b10100110 #
b10100110 )
b10100110 !
b10100110 *
b1010011 "
b1010011 (
b1010011 &
1$
1%
#168
b10101000 #
b10101000 )
b10101000 !
b10101000 *
b1010100 "
b1010100 (
b1010100 &
1$
1%
#170
b10101010 #
b10101010 )
b10101010 !
b10101010 *
b1010101 "
b1010101 (
b1010101 &
1$
1%
#172
b10101100 #
b10101100 )
b10101100 !
b10101100 *
b1010110 "
b1010110 (
b1010110 &
1$
1%
#174
b10101110 #
b10101110 )
b10101110 !
b10101110 *
b1010111 "
b1010111 (
b1010111 &
1$
1%
#176
b10110000 #
b10110000 )
b10110000 !
b10110000 *
b1011000 "
b1011000 (
b1011000 &
1$
1%
#178
b10110010 #
b10110010 )
b10110010 !
b10110010 *
b1011001 "
b1011001 (
b1011001 &
1$
1%
#180
b10110100 #
b10110100 )
b10110100 !
b10110100 *
b1011010 "
b1011010 (
b1011010 &
1$
1%
#182
b10110110 #
b10110110 )
b10110110 !
b10110110 *
b1011011 "
b1011011 (
b1011011 &
1$
1%
#184
b10111000 #
b10111000 )
b10111000 !
b10111000 *
b1011100 "
b1011100 (
b1011100 &
1$
1%
#186
b10111010 #
b10111010 )
b10111010 !
b10111010 *
b1011101 "
b1011101 (
b1011101 &
1$
1%
#188
b10111100 #
b10111100 )
b10111100 !
b10111100 *
b1011110 "
b1011110 (
b1011110 &
1$
1%
#190
b10111110 #
b10111110 )
b10111110 !
b10111110 *
b1011111 "
b1011111 (
b1011111 &
1$
1%
#192
b11000000 #
b11000000 )
b11000000 !
b11000000 *
b1100000 "
b1100000 (
b1100000 &
1$
1%
#194
b11000010 #
b11000010 )
b11000010 !
b11000010 *
b1100001 "
b1100001 (
b1100001 &
1$
1%
#196
b11000100 #
b11000100 )
b11000100 !
b11000100 *
b1100010 "
b1100010 (
b1100010 &
1$
1%
#198
b11000110 #
b11000110 )
b11000110 !
b11000110 *
b1100011 "
b1100011 (
b1100011 &
1$
1%
#200
b11001000 #
b11001000 )
b11001000 !
b11001000 *
b1100100 "
b1100100 (
b1100100 &
1$
1%
#202
b11001010 #
b11001010 )
b11001010 !
b11001010 *
b1100101 "
b1100101 (
b1100101 &
1$
1%
#204
b11001100 #
b11001100 )
b11001100 !
b11001100 *
b1100110 "
b1100110 (
b1100110 &
1$
1%
#206
b11001110 #
b11001110 )
b11001110 !
b11001110 *
b1100111 "
b1100111 (
b1100111 &
1$
1%
#208
b11010000 #
b11010000 )
b11010000 !
b11010000 *
b1101000 "
b1101000 (
b1101000 &
1$
1%
#210
b11010010 #
b11010010 )
b11010010 !
b11010010 *
b1101001 "
b1101001 (
b1101001 &
1$
1%
#212
b11010100 #
b11010100 )
b11010100 !
b11010100 *
b1101010 "
b1101010 (
b1101010 &
1$
1%
#214
b11010110 #
b11010110 )
b11010110 !
b11010110 *
b1101011 "
b1101011 (
b1101011 &
1$
1%
#216
b11011000 #
b11011000 )
b11011000 !
b11011000 *
b1101100 "
b1101100 (
b1101100 &
1$
1%
#218
b11011010 #
b11011010 )
b11011010 !
b11011010 *
b1101101 "
b1101101 (
b1101101 &
1$
1%
#220
b11011100 #
b11011100 )
b11011100 !
b11011100 *
b1101110 "
b1101110 (
b1101110 &
1$
1%
#222
b11011110 #
b11011110 )
b11011110 !
b11011110 *
b1101111 "
b1101111 (
b1101111 &
1$
1%
#224
b11100000 #
b11100000 )
b11100000 !
b11100000 *
b1110000 "
b1110000 (
b1110000 &
1$
1%
#226
b11100010 #
b11100010 )
b11100010 !
b11100010 *
b1110001 "
b1110001 (
b1110001 &
1$
1%
#228
b11100100 #
b11100100 )
b11100100 !
b11100100 *
b1110010 "
b1110010 (
b1110010 &
1$
1%
#230
b11100110 #
b11100110 )
b11100110 !
b11100110 *
b1110011 "
b1110011 (
b1110011 &
1$
1%
#232
b11101000 #
b11101000 )
b11101000 !
b11101000 *
b1110100 "
b1110100 (
b1110100 &
1$
1%
#234
b11101010 #
b11101010 )
b11101010 !
b11101010 *
b1110101 "
b1110101 (
b1110101 &
1$
1%
#236
b11101100 #
b11101100 )
b11101100 !
b11101100 *
b1110110 "
b1110110 (
b1110110 &
1$
1%
#238
b11101110 #
b11101110 )
b11101110 !
b11101110 *
b1110111 "
b1110111 (
b1110111 &
1$
1%
#240
b11110000 #
b11110000 )
b11110000 !
b11110000 *
b1111000 "
b1111000 (
b1111000 &
1$
1%
#242
b11110010 #
b11110010 )
b11110010 !
b11110010 *
b1111001 "
b1111001 (
b1111001 &
1$
1%
#244
b11110100 #
b11110100 )
b11110100 !
b11110100 *
b1111010 "
b1111010 (
b1111010 &
1$
1%
#246
b11110110 #
b11110110 )
b11110110 !
b11110110 *
b1111011 "
b1111011 (
b1111011 &
1$
1%
#248
b11111000 #
b11111000 )
b11111000 !
b11111000 *
b1111100 "
b1111100 (
b1111100 &
1$
1%
#250
b11111010 #
b11111010 )
b11111010 !
b11111010 *
b1111101 "
b1111101 (
b1111101 &
1$
1%
#252
b11111100 #
b11111100 )
b11111100 !
b11111100 *
b1111110 "
b1111110 (
b1111110 &
1$
1%
#254
b11111110 #
b11111110 )
b11111110 !
b11111110 *
b1111111 "
b1111111 (
b1111111 &
1$
1%
#256
b0 #
b0 )
b0 !
b0 *
b10000000 "
b10000000 (
b10000000 &
1$
1%
#258
b10 #
b10 )
b10 !
b10 *
b10000001 "
b10000001 (
b10000001 &
1$
1%
#260
b100 #
b100 )
b100 !
b100 *
b10000010 "
b10000010 (
b10000010 &
1$
1%
#262
b110 #
b110 )
b110 !
b110 *
b10000011 "
b10000011 (
b10000011 &
1$
1%
#264
b1000 #
b1000 )
b1000 !
b1000 *
b10000100 "
b10000100 (
b10000100 &
1$
1%
#266
b1010 #
b1010 )
b1010 !
b1010 *
b10000101 "
b10000101 (
b10000101 &
1$
1%
#268
b1100 #
b1100 )
b1100 !
b1100 *
b10000110 "
b10000110 (
b10000110 &
1$
1%
#270
b1110 #
b1110 )
b1110 !
b1110 *
b10000111 "
b10000111 (
b10000111 &
1$
1%
#272
b10000 #
b10000 )
b10000 !
b10000 *
b10001000 "
b10001000 (
b10001000 &
1$
1%
#274
b10010 #
b10010 )
b10010 !
b10010 *
b10001001 "
b10001001 (
b10001001 &
1$
1%
#276
b10100 #
b10100 )
b10100 !
b10100 *
b10001010 "
b10001010 (
b10001010 &
1$
1%
#278
b10110 #
b10110 )
b10110 !
b10110 *
b10001011 "
b10001011 (
b10001011 &
1$
1%
#280
b11000 #
b11000 )
b11000 !
b11000 *
b10001100 "
b10001100 (
b10001100 &
1$
1%
#282
b11010 #
b11010 )
b11010 !
b11010 *
b10001101 "
b10001101 (
b10001101 &
1$
1%
#284
b11100 #
b11100 )
b11100 !
b11100 *
b10001110 "
b10001110 (
b10001110 &
1$
1%
#286
b11110 #
b11110 )
b11110 !
b11110 *
b10001111 "
b10001111 (
b10001111 &
1$
1%
#288
b100000 #
b100000 )
b100000 !
b100000 *
b10010000 "
b10010000 (
b10010000 &
1$
1%
#290
b100010 #
b100010 )
b100010 !
b100010 *
b10010001 "
b10010001 (
b10010001 &
1$
1%
#292
b100100 #
b100100 )
b100100 !
b100100 *
b10010010 "
b10010010 (
b10010010 &
1$
1%
#294
b100110 #
b100110 )
b100110 !
b100110 *
b10010011 "
b10010011 (
b10010011 &
1$
1%
#296
b101000 #
b101000 )
b101000 !
b101000 *
b10010100 "
b10010100 (
b10010100 &
1$
1%
#298
b101010 #
b101010 )
b101010 !
b101010 *
b10010101 "
b10010101 (
b10010101 &
1$
1%
#300
b101100 #
b101100 )
b101100 !
b101100 *
b10010110 "
b10010110 (
b10010110 &
1$
1%
#302
b101110 #
b101110 )
b101110 !
b101110 *
b10010111 "
b10010111 (
b10010111 &
1$
1%
#304
b110000 #
b110000 )
b110000 !
b110000 *
b10011000 "
b10011000 (
b10011000 &
1$
1%
#306
b110010 #
b110010 )
b110010 !
b110010 *
b10011001 "
b10011001 (
b10011001 &
1$
1%
#308
b110100 #
b110100 )
b110100 !
b110100 *
b10011010 "
b10011010 (
b10011010 &
1$
1%
#310
b110110 #
b110110 )
b110110 !
b110110 *
b10011011 "
b10011011 (
b10011011 &
1$
1%
#312
b111000 #
b111000 )
b111000 !
b111000 *
b10011100 "
b10011100 (
b10011100 &
1$
1%
#314
b111010 #
b111010 )
b111010 !
b111010 *
b10011101 "
b10011101 (
b10011101 &
1$
1%
#316
b111100 #
b111100 )
b111100 !
b111100 *
b10011110 "
b10011110 (
b10011110 &
1$
1%
#318
b111110 #
b111110 )
b111110 !
b111110 *
b10011111 "
b10011111 (
b10011111 &
1$
1%
#320
b1000000 #
b1000000 )
b1000000 !
b1000000 *
b10100000 "
b10100000 (
b10100000 &
1$
1%
#322
b1000010 #
b1000010 )
b1000010 !
b1000010 *
b10100001 "
b10100001 (
b10100001 &
1$
1%
#324
b1000100 #
b1000100 )
b1000100 !
b1000100 *
b10100010 "
b10100010 (
b10100010 &
1$
1%
#326
b1000110 #
b1000110 )
b1000110 !
b1000110 *
b10100011 "
b10100011 (
b10100011 &
1$
1%
#328
b1001000 #
b1001000 )
b1001000 !
b1001000 *
b10100100 "
b10100100 (
b10100100 &
1$
1%
#330
b1001010 #
b1001010 )
b1001010 !
b1001010 *
b10100101 "
b10100101 (
b10100101 &
1$
1%
#332
b1001100 #
b1001100 )
b1001100 !
b1001100 *
b10100110 "
b10100110 (
b10100110 &
1$
1%
#334
b1001110 #
b1001110 )
b1001110 !
b1001110 *
b10100111 "
b10100111 (
b10100111 &
1$
1%
#336
b1010000 #
b1010000 )
b1010000 !
b1010000 *
b10101000 "
b10101000 (
b10101000 &
1$
1%
#338
b1010010 #
b1010010 )
b1010010 !
b1010010 *
b10101001 "
b10101001 (
b10101001 &
1$
1%
#340
b1010100 #
b1010100 )
b1010100 !
b1010100 *
b10101010 "
b10101010 (
b10101010 &
1$
1%
#342
b1010110 #
b1010110 )
b1010110 !
b1010110 *
b10101011 "
b10101011 (
b10101011 &
1$
1%
#344
b1011000 #
b1011000 )
b1011000 !
b1011000 *
b10101100 "
b10101100 (
b10101100 &
1$
1%
#346
b1011010 #
b1011010 )
b1011010 !
b1011010 *
b10101101 "
b10101101 (
b10101101 &
1$
1%
#348
b1011100 #
b1011100 )
b1011100 !
b1011100 *
b10101110 "
b10101110 (
b10101110 &
1$
1%
#350
b1011110 #
b1011110 )
b1011110 !
b1011110 *
b10101111 "
b10101111 (
b10101111 &
1$
1%
#352
b1100000 #
b1100000 )
b1100000 !
b1100000 *
b10110000 "
b10110000 (
b10110000 &
1$
1%
#354
b1100010 #
b1100010 )
b1100010 !
b1100010 *
b10110001 "
b10110001 (
b10110001 &
1$
1%
#356
b1100100 #
b1100100 )
b1100100 !
b1100100 *
b10110010 "
b10110010 (
b10110010 &
1$
1%
#358
b1100110 #
b1100110 )
b1100110 !
b1100110 *
b10110011 "
b10110011 (
b10110011 &
1$
1%
#360
b1101000 #
b1101000 )
b1101000 !
b1101000 *
b10110100 "
b10110100 (
b10110100 &
1$
1%
#362
b1101010 #
b1101010 )
b1101010 !
b1101010 *
b10110101 "
b10110101 (
b10110101 &
1$
1%
#364
b1101100 #
b1101100 )
b1101100 !
b1101100 *
b10110110 "
b10110110 (
b10110110 &
1$
1%
#366
b1101110 #
b1101110 )
b1101110 !
b1101110 *
b10110111 "
b10110111 (
b10110111 &
1$
1%
#368
b1110000 #
b1110000 )
b1110000 !
b1110000 *
b10111000 "
b10111000 (
b10111000 &
1$
1%
#370
b1110010 #
b1110010 )
b1110010 !
b1110010 *
b10111001 "
b10111001 (
b10111001 &
1$
1%
#372
b1110100 #
b1110100 )
b1110100 !
b1110100 *
b10111010 "
b10111010 (
b10111010 &
1$
1%
#374
b1110110 #
b1110110 )
b1110110 !
b1110110 *
b10111011 "
b10111011 (
b10111011 &
1$
1%
#376
b1111000 #
b1111000 )
b1111000 !
b1111000 *
b10111100 "
b10111100 (
b10111100 &
1$
1%
#378
b1111010 #
b1111010 )
b1111010 !
b1111010 *
b10111101 "
b10111101 (
b10111101 &
1$
1%
#380
b1111100 #
b1111100 )
b1111100 !
b1111100 *
b10111110 "
b10111110 (
b10111110 &
1$
1%
#382
b1111110 #
b1111110 )
b1111110 !
b1111110 *
b10111111 "
b10111111 (
b10111111 &
1$
1%
#384
b10000000 #
b10000000 )
b10000000 !
b10000000 *
b11000000 "
b11000000 (
b11000000 &
1$
1%
#386
b10000010 #
b10000010 )
b10000010 !
b10000010 *
b11000001 "
b11000001 (
b11000001 &
1$
1%
#388
b10000100 #
b10000100 )
b10000100 !
b10000100 *
b11000010 "
b11000010 (
b11000010 &
1$
1%
#390
b10000110 #
b10000110 )
b10000110 !
b10000110 *
b11000011 "
b11000011 (
b11000011 &
1$
1%
#392
b10001000 #
b10001000 )
b10001000 !
b10001000 *
b11000100 "
b11000100 (
b11000100 &
1$
1%
#394
b10001010 #
b10001010 )
b10001010 !
b10001010 *
b11000101 "
b11000101 (
b11000101 &
1$
1%
#396
b10001100 #
b10001100 )
b10001100 !
b10001100 *
b11000110 "
b11000110 (
b11000110 &
1$
1%
#398
b10001110 #
b10001110 )
b10001110 !
b10001110 *
b11000111 "
b11000111 (
b11000111 &
1$
1%
#400
b10010000 #
b10010000 )
b10010000 !
b10010000 *
b11001000 "
b11001000 (
b11001000 &
1$
1%
#402
b10010010 #
b10010010 )
b10010010 !
b10010010 *
b11001001 "
b11001001 (
b11001001 &
1$
1%
#404
b10010100 #
b10010100 )
b10010100 !
b10010100 *
b11001010 "
b11001010 (
b11001010 &
1$
1%
#406
b10010110 #
b10010110 )
b10010110 !
b10010110 *
b11001011 "
b11001011 (
b11001011 &
1$
1%
#408
b10011000 #
b10011000 )
b10011000 !
b10011000 *
b11001100 "
b11001100 (
b11001100 &
1$
1%
#410
b10011010 #
b10011010 )
b10011010 !
b10011010 *
b11001101 "
b11001101 (
b11001101 &
1$
1%
#412
b10011100 #
b10011100 )
b10011100 !
b10011100 *
b11001110 "
b11001110 (
b11001110 &
1$
1%
#414
b10011110 #
b10011110 )
b10011110 !
b10011110 *
b11001111 "
b11001111 (
b11001111 &
1$
1%
#416
b10100000 #
b10100000 )
b10100000 !
b10100000 *
b11010000 "
b11010000 (
b11010000 &
1$
1%
#418
b10100010 #
b10100010 )
b10100010 !
b10100010 *
b11010001 "
b11010001 (
b11010001 &
1$
1%
#420
b10100100 #
b10100100 )
b10100100 !
b10100100 *
b11010010 "
b11010010 (
b11010010 &
1$
1%
#422
b10100110 #
b10100110 )
b10100110 !
b10100110 *
b11010011 "
b11010011 (
b11010011 &
1$
1%
#424
b10101000 #
b10101000 )
b10101000 !
b10101000 *
b11010100 "
b11010100 (
b11010100 &
1$
1%
#426
b10101010 #
b10101010 )
b10101010 !
b10101010 *
b11010101 "
b11010101 (
b11010101 &
1$
1%
#428
b10101100 #
b10101100 )
b10101100 !
b10101100 *
b11010110 "
b11010110 (
b11010110 &
1$
1%
#430
b10101110 #
b10101110 )
b10101110 !
b10101110 *
b11010111 "
b11010111 (
b11010111 &
1$
1%
#432
b10110000 #
b10110000 )
b10110000 !
b10110000 *
b11011000 "
b11011000 (
b11011000 &
1$
1%
#434
b10110010 #
b10110010 )
b10110010 !
b10110010 *
b11011001 "
b11011001 (
b11011001 &
1$
1%
#436
b10110100 #
b10110100 )
b10110100 !
b10110100 *
b11011010 "
b11011010 (
b11011010 &
1$
1%
#438
b10110110 #
b10110110 )
b10110110 !
b10110110 *
b11011011 "
b11011011 (
b11011011 &
1$
1%
#440
b10111000 #
b10111000 )
b10111000 !
b10111000 *
b11011100 "
b11011100 (
b11011100 &
1$
1%
#442
b10111010 #
b10111010 )
b10111010 !
b10111010 *
b11011101 "
b11011101 (
b11011101 &
1$
1%
#444
b10111100 #
b10111100 )
b10111100 !
b10111100 *
b11011110 "
b11011110 (
b11011110 &
1$
1%
#446
b10111110 #
b10111110 )
b10111110 !
b10111110 *
b11011111 "
b11011111 (
b11011111 &
1$
1%
#448
b11000000 #
b11000000 )
b11000000 !
b11000000 *
b11100000 "
b11100000 (
b11100000 &
1$
1%
#450
b11000010 #
b11000010 )
b11000010 !
b11000010 *
b11100001 "
b11100001 (
b11100001 &
1$
1%
#452
b11000100 #
b11000100 )
b11000100 !
b11000100 *
b11100010 "
b11100010 (
b11100010 &
1$
1%
#454
b11000110 #
b11000110 )
b11000110 !
b11000110 *
b11100011 "
b11100011 (
b11100011 &
1$
1%
#456
b11001000 #
b11001000 )
b11001000 !
b11001000 *
b11100100 "
b11100100 (
b11100100 &
1$
1%
#458
b11001010 #
b11001010 )
b11001010 !
b11001010 *
b11100101 "
b11100101 (
b11100101 &
1$
1%
#460
b11001100 #
b11001100 )
b11001100 !
b11001100 *
b11100110 "
b11100110 (
b11100110 &
1$
1%
#462
b11001110 #
b11001110 )
b11001110 !
b11001110 *
b11100111 "
b11100111 (
b11100111 &
1$
1%
#464
b11010000 #
b11010000 )
b11010000 !
b11010000 *
b11101000 "
b11101000 (
b11101000 &
1$
1%
#466
b11010010 #
b11010010 )
b11010010 !
b11010010 *
b11101001 "
b11101001 (
b11101001 &
1$
1%
#468
b11010100 #
b11010100 )
b11010100 !
b11010100 *
b11101010 "
b11101010 (
b11101010 &
1$
1%
#470
b11010110 #
b11010110 )
b11010110 !
b11010110 *
b11101011 "
b11101011 (
b11101011 &
1$
1%
#472
b11011000 #
b11011000 )
b11011000 !
b11011000 *
b11101100 "
b11101100 (
b11101100 &
1$
1%
#474
b11011010 #
b11011010 )
b11011010 !
b11011010 *
b11101101 "
b11101101 (
b11101101 &
1$
1%
#476
b11011100 #
b11011100 )
b11011100 !
b11011100 *
b11101110 "
b11101110 (
b11101110 &
1$
1%
#478
b11011110 #
b11011110 )
b11011110 !
b11011110 *
b11101111 "
b11101111 (
b11101111 &
1$
1%
#480
b11100000 #
b11100000 )
b11100000 !
b11100000 *
b11110000 "
b11110000 (
b11110000 &
1$
1%
#482
b11100010 #
b11100010 )
b11100010 !
b11100010 *
b11110001 "
b11110001 (
b11110001 &
1$
1%
#484
b11100100 #
b11100100 )
b11100100 !
b11100100 *
b11110010 "
b11110010 (
b11110010 &
1$
1%
#486
b11100110 #
b11100110 )
b11100110 !
b11100110 *
b11110011 "
b11110011 (
b11110011 &
1$
1%
#488
b11101000 #
b11101000 )
b11101000 !
b11101000 *
b11110100 "
b11110100 (
b11110100 &
1$
1%
#490
b11101010 #
b11101010 )
b11101010 !
b11101010 *
b11110101 "
b11110101 (
b11110101 &
1$
1%
#492
b11101100 #
b11101100 )
b11101100 !
b11101100 *
b11110110 "
b11110110 (
b11110110 &
1$
1%
#494
b11101110 #
b11101110 )
b11101110 !
b11101110 *
b11110111 "
b11110111 (
b11110111 &
1$
1%
#496
b11110000 #
b11110000 )
b11110000 !
b11110000 *
b11111000 "
b11111000 (
b11111000 &
1$
1%
#498
b11110010 #
b11110010 )
b11110010 !
b11110010 *
b11111001 "
b11111001 (
b11111001 &
1$
1%
#500
b11110100 #
b11110100 )
b11110100 !
b11110100 *
b11111010 "
b11111010 (
b11111010 &
1$
1%
