Day_007/jk_ff.v
module jk_ff (Q, Qb, J, K, Clk, Set, Rst);
  input J, K, Clk, Set, Rst;
  output Q, Qb;
  wire [6:0] t;
  
  not g1 (t[0], Clk);

  nand g2(t[1], Qb, J, Clk),
       g3(t[2], Q, K, Clk),
       g4(t[3], t[1], t[4]),
       g5(t[4], t[2], t[3]),
       g6(t[5], t[3], t[0]),
       g7(t[6], t[4], t[0]),
       g8(Q, t[5], Qb, Set),
       g9(Qb, t[6], Q, Rst);

endmodule

Day_007/jk_ff_tb.v
module tb_jk_ff;
  reg J, K, Clk, Set, Rst;
  wire Q, Qb;
  jk_ff uut (.J(J), .K(K), .Clk(Clk), .Set(Set), .Rst(Rst), .Q(Q), .Qb(Qb));
  
    initial begin
    Clk = 0;
    forever #5 Clk = ~Clk;
  end
  
  initial begin
    $dumpfile("tb_jk_ff.vcd");
    $dumpvars(0, tb_jk_ff);
    
    // Scenario 1: Set and Reset both active (not allowed behavior)
    #10; J = 1'b0; K = 1'b0; Set = 1'b1; Rst = 1'b1;
    
    // Scenario 2: Set active, then Reset active (not allowed behavior)
    #10; Set = 1'b1; Rst = 1'b0;
    #10; Set = 1'b0; Rst = 1'b1;
    
    // Scenario 3: J and K both inactive (toggle behavior)
    #10; Set = 1'b0; Rst = 1'b0; J = 1'b0; K = 1'b0;
    
    // Scenario 4: J active (set behavior)
    #10; J = 1'b1;
    
    // Scenario 5: K active (reset behavior)
    #10; J = 1'b0; K = 1'b1;
    
    // Scenario 6: Set active (set behavior)
    #10; K = 1'b0; Set = 1'b1;
    
    // Scenario 7: Reset active (reset behavior)
    #10; Set = 1'b0; Rst = 1'b1;
    
    // Scenario 8: J and K both active (toggle behavior)
    #10; J = 1'b1; K = 1'b1;
    
    // Wait for simulation to finish
    #10;
    $finish;
  end
  
  // Monitor outputs
  always @(Q or Qb)
    $display($time, " Q = %b, Qb = %b", Q, Qb);
  
endmodule

Day_007/tb_jk_ff.vcd
$date
	Wed Aug 30 23:25:15 2023
$end
$version
	Icarus Verilog
$end
$timescale
	1s
$end
$scope module tb_jk_ff $end
$var wire 1 ! Qb $end
$var wire 1 " Q $end
$var reg 1 # Clk $end
$var reg 1 $ J $end
$var reg 1 % K $end
$var reg 1 & Rst $end
$var reg 1 ' Set $end
$scope module uut $end
$var wire 1 # Clk $end
$var wire 1 $ J $end
$var wire 1 % K $end
$var wire 1 " Q $end
$var wire 1 ! Qb $end
$var wire 1 & Rst $end
$var wire 1 ' Set $end
$var wire 7 ( t [6:0] $end
$upscope $end
$upscope $end
$enddefinitions $end
$comment Show the parameter values. $end
$dumpall
$end
#0
$dumpvars
bx111 (
x'
x&
x%
x$
0#
x"
x!
$end
#5
b11xxxx0 (
1#
#10
bx111 (
0#
1&
1'
0%
0$
#15
b11xx110 (
1#
#20
x"
bx111 (
1!
0#
0&
#25
0"
b11xx110 (
1#
#30
bx111 (
x!
1"
0#
1&
0'
#35
0!
b11xx110 (
1#
#40
bx111 (
1!
0#
0&
#45
b11xx110 (
1#
#50
bx111 (
0#
1$
#55
b1101100 (
1#
#60
b1001111 (
0#
1%
0$
#65
b1110010 (
1#
#70
0"
b110111 (
0#
1'
0%
#75
b1110110 (
1#
#80
b110111 (
1!
1"
0#
1&
0'
#85
0!
b1110110 (
1#
#90
1!
b110111 (
0#
1%
1$
#95
0!
b1110010 (
1#
#100
1!
b110111 (
0#
