Day_014/parity_gen.v
module serial_paritity_gen (x,clk,z);
    input x,clk;
    output reg z;
    reg even_odd;
    parameter EVEN=0, ODD=1;
    always @ (posedge clk) begin
        case (even_odd)
            EVEN: even_odd <= x? ODD:EVEN;
            ODD: even_odd <= x? EVEN:ODD;
            default: even_odd <= EVEN;
        endcase
    end
    always @ (even_odd) begin
        case (even_odd)
            EVEN: z= 0;
            ODD: z = 1;
        endcase
    end
endmodule

Day_014/parity_gen_tb.v
module serial_paritity_gen_tb;
    reg x,clk;
    wire z;
    serial_paritity_gen uut(.x(x), .clk(clk), .z(z));
    initial begin
        $dumpfile("serial_parity.vcd");
        $dumpvars(0,serial_paritity_gen_tb);
        $monitor($time," x=%b  z=%b",x,z);
        clk=1'b0;
    end
    always #5 clk=~clk;
    initial begin
        #2 x=0; #10 x=1; #10 x=0; #10 x=1; #10 x=1; #10 x=0;
        #10 x=0; #10 x=1; #10 x=0; #10 x=0; #10 x=1; #10 x=0;
        #10 x=1; #10 x=1; #10 x=0; #10 x=0; #10 x=1; #10 x=0;
        #10 $finish;
    end
endmodule

Day_014/serial_parity.vcd
$date
	Fri Sep  8 19:32:09 2023
$end
$version
	Icarus Verilog
$end
$timescale
	1s
$end
$scope module serial_paritity_gen_tb $end
$var wire 1 ! z $end
$var reg 1 " clk $end
$var reg 1 # x $end
$scope module uut $end
$var wire 1 " clk $end
$var wire 1 # x $end
$var parameter 32 $ EVEN $end
$var parameter 32 % ODD $end
$var reg 1 & even_odd $end
$var reg 1 ! z $end
$upscope $end
$upscope $end
$enddefinitions $end
$comment Show the parameter values. $end
$dumpall
b1 %
b0 $
$end
#0
$dumpvars
x&
x#
0"
x!
$end
#2
0#
#5
0!
0&
1"
#10
0"
#12
1#
#15
1!
1&
1"
#20
0"
#22
0#
#25
1"
#30
0"
#32
1#
#35
0!
0&
1"
#40
0"
#45
1!
1&
1"
#50
0"
#52
0#
#55
1"
#60
0"
#65
1"
#70
0"
#72
1#
#75
0!
0&
1"
#80
0"
#82
0#
#85
1"
#90
0"
#95
1"
#100
0"
#102
1#
#105
1!
1&
1"
#110
0"
#112
0#
#115
1"
#120
0"
#122
1#
#125
0!
0&
1"
#130
0"
#135
1!
1&
1"
#140
0"
#142
0#
#145
1"
#150
0"
#155
1"
#160
0"
#162
1#
#165
0!
0&
1"
#170
0"
#172
0#
