Day_002/bcd.v
module BCD_to_Excess3 (
    input [3:0] bcd_in,
    output [9:0] excess3_out
);

    wire [9:0] decoder_out;

    decoder_4to10 decoder (
        .inputs(bcd_in),
        .outputs(decoder_out)
    );

    assign excess3_out[0] = 1'b0; // Bit 0 always 0
    assign excess3_out[1] = 1'b1; // Bit 1 always 1
    assign excess3_out[2] = ~decoder_out[0]; // Bit 2 is the complement of decoder_out[0]
    assign excess3_out[3] = ~decoder_out[1]; // Bit 3 is the complement of decoder_out[1]
    assign excess3_out[4] = ~decoder_out[2]; // Bit 4 is the complement of decoder_out[2]
    assign excess3_out[5] = ~decoder_out[3]; // Bit 5 is the complement of decoder_out[3]
    assign excess3_out[6] = decoder_out[4];  // Bit 6 is same as decoder_out[4]
    assign excess3_out[7] = decoder_out[5];  // Bit 7 is same as decoder_out[5]
    assign excess3_out[8] = decoder_out[6];  // Bit 8 is same as decoder_out[6]
    assign excess3_out[9] = decoder_out[7];  // Bit 9 is same as decoder_out[7]

endmodule

// 4-to-10 decoder module
module decoder_4to10 (
    input [3:0] inputs,
    output [9:0] outputs
);
    wire [15:0] and_terms; 

    assign and_terms[0]  = inputs[0] & inputs[1] & inputs[2] & inputs[3];
    assign and_terms[1]  = inputs[0] & inputs[1] & inputs[2] & ~inputs[3];
    assign and_terms[2]  = inputs[0] & inputs[1] & ~inputs[2] & inputs[3];
    assign and_terms[3]  = inputs[0] & inputs[1] & ~inputs[2] & ~inputs[3];
    assign and_terms[4]  = inputs[0] & ~inputs[1] & inputs[2] & inputs[3];
    assign and_terms[5]  = inputs[0] & ~inputs[1] & inputs[2] & ~inputs[3];
    assign and_terms[6]  = inputs[0] & ~inputs[1] & ~inputs[2] & inputs[3];
    assign and_terms[7]  = inputs[0] & ~inputs[1] & ~inputs[2] & ~inputs[3];
    assign and_terms[8]  = ~inputs[0] & inputs[1] & inputs[2] & inputs[3];
    assign and_terms[9]  = ~inputs[0] & inputs[1] & inputs[2] & ~inputs[3];
    assign and_terms[10] = ~inputs[0] & inputs[1] & ~inputs[2] & inputs[3];
    assign and_terms[11] = ~inputs[0] & inputs[1] & ~inputs[2] & ~inputs[3];
    assign and_terms[12] = ~inputs[0] & ~inputs[1] & inputs[2] & inputs[3];
    assign and_terms[13] = ~inputs[0] & ~inputs[1] & inputs[2] & ~inputs[3];
    assign and_terms[14] = ~inputs[0] & ~inputs[1] & ~inputs[2] & inputs[3];
    assign and_terms[15] = ~inputs[0] & ~inputs[1] & ~inputs[2] & ~inputs[3];
    assign outputs[0] = and_terms[0] | and_terms[1];
    assign outputs[1] = and_terms[2] | and_terms[3];
    assign outputs[2] = and_terms[4] | and_terms[5];
    assign outputs[3] = and_terms[6] | and_terms[7];
    assign outputs[4] = and_terms[8] | and_terms[9];
    assign outputs[5] = and_terms[10] | and_terms[11];
    assign outputs[6] = and_terms[12] | and_terms[13];
    assign outputs[7] = and_terms[14] | and_terms[15];
    assign outputs[8] = and_terms[0] | and_terms[1] | and_terms[4] | and_terms[5] | and_terms[8] | and_terms[9] | and_terms[12] | and_terms[13];
    assign outputs[9] = and_terms[2] | and_terms[3] | and_terms[6] | and_terms[7] | and_terms[10] | and_terms[11] | and_terms[14] | and_terms[15];

endmodule

Day_002/bcd_tb.v
module tb_BCD_to_Excess3;

    // Parameters
    reg [3:0] bcd_in;
    wire [9:0] excess3_out;

    // Instantiate the BCD to Excess-3 converter
    BCD_to_Excess3 uut (
        .bcd_in(bcd_in),
        .excess3_out(excess3_out)
    );

    // Clock generation
    reg clk;
    always #5 clk = ~clk;

    // Testbench behavior
    initial begin
        $dumpfile ("bcd.vcd");
        $dumpvars (0,tb_BCD_to_Excess3);
        // Initialize clock
        clk = 0;

        // Test different BCD input values
        for (bcd_in = 0; bcd_in < 10; bcd_in = bcd_in + 1) begin
            #10; // Wait for a few clock cycles
            
            // Display input and output
            $display("BCD Input: %d, Excess-3 Output: %b", bcd_in, excess3_out);
        end

        $finish; // End simulation
    end

endmodule

Day_002/bcd.vcd
$date
	Tue Aug 15 11:46:07 2023
$end
$version
	Icarus Verilog
$end
$timescale
	1s
$end
$scope module tb_BCD_to_Excess3 $end
$var wire 10 ! excess3_out [9:0] $end
$var reg 4 " bcd_in [3:0] $end
$var reg 1 # clk $end
$scope module uut $end
$var wire 4 $ bcd_in [3:0] $end
$var wire 10 % excess3_out [9:0] $end
$var wire 10 & decoder_out [9:0] $end
$scope module decoder $end
$var wire 4 ' inputs [3:0] $end
$var wire 10 ( outputs [9:0] $end
$var wire 16 ) and_terms [15:0] $end
$upscope $end
$upscope $end
$upscope $end
$enddefinitions $end
$comment Show the parameter values. $end
$dumpall
$end
#0
$dumpvars
b1000000000000000 )
b1010000000 (
b0 '
b1010000000 &
b1000111110 %
b0 $
0#
b0 "
b1000111110 !
$end
#5
1#
#10
b11110 !
b11110 %
b1000001000 &
b1000001000 (
b10000000 )
0#
b1 "
b1 $
b1 '
#15
1#
#20
b10111110 !
b10111110 %
b1000100000 &
b1000100000 (
b100000000000 )
0#
b10 "
b10 $
b10 '
#25
1#
#30
b110110 !
b110110 %
b1000000010 &
b1000000010 (
b1000 )
0#
b11 "
b11 $
b11 '
#35
1#
#40
b100111110 !
b100111110 %
b101000000 &
b101000000 (
b10000000000000 )
0#
b100 "
b100 $
b100 '
#45
1#
#50
b101110 !
b101110 %
b100000100 &
b100000100 (
b100000 )
0#
b101 "
b101 $
b101 '
#55
1#
#60
b1111110 !
b1111110 %
b100010000 &
b100010000 (
b1000000000 )
0#
b110 "
b110 $
b110 '
#65
1#
#70
b111010 !
b111010 %
b100000001 &
b100000001 (
b10 )
0#
b111 "
b111 $
b111 '
#75
1#
#80
b1000111110 !
b1000111110 %
b1010000000 &
b1010000000 (
b100000000000000 )
0#
b1000 "
b1000 $
b1000 '
#85
1#
#90
b11110 !
b11110 %
b1000001000 &
b1000001000 (
b1000000 )
0#
b1001 "
b1001 $
b1001 '
#95
1#
#100
b10111110 !
b10111110 %
b1000100000 &
b1000100000 (
b10000000000 )
0#
b1010 "
b1010 $
b1010 '
