Day_018/pipe.v
module pipe(F, A, B, C, D, clk);
parameter N = 10;
input [N-1:0] A, B, C, D;
input clk;
output [N-1:0] F;
reg [N-1:0] L12_x1, L12_x2, L12_D, L23_x3, L23_D, L34_F;
assign F = L34_F;
always @(posedge clk) // ** STAGE 1 **
begin
L12_x1 <= #4 A + B;
L12_x2 <= #4 C - D;
L12_D <= D;
end
always @(posedge clk) // ** STAGE 2 **
begin
L23_x3 <= #4 L12_x1 + L12_x2;
L23_D <= L12_D;
end

always @(posedge clk) // ** STAGE 3 **
L34_F <= #6 L23_x3 * L23_D;

endmodule

Day_018/pipe_tb.v
module pipe_tb;
parameter N = 10;
wire [N-1:0] F;
reg [N-1:0] A, B, C, D;
reg clk;
pipe UUT (F, A, B, C, D, clk);
initial clk = 0;
always #10 clk = ~clk;
initial
begin
#5 A = 10; B = 12; C = 6; D = 3; // F = 75 (4Bh)
#20 A = 10; B = 10; C = 5; D = 3; // F = 66 (42h)
#20 A = 20; B = 11; C = 1; D = 4; // F = 112 (70h)
#20 A = 15; B = 10; C = 8; D = 2; // F = 62 (3Eh)
#20 A = 8; B = 15; C = 5; D = 0; // F = 0 (00h)
#20 A = 10; B = 20; C = 5; D = 3; // F = 66 (42h)
#20 A = 10; B = 10; C = 30; D = 1; // F = 49 (31h)
#20 A = 30; B = 1; C = 2; D = 4; // F = 116 (74h)
end
initial
begin
$dumpfile ("pipe.vcd");
$dumpvars (0,pipe_tb);
$monitor ("Time: %d, F = %d", $time, F);
#300 $finish;
end
endmodule

Day_018/pipe.vcd
$date
	Sat Sep 23 22:32:45 2023
$end
$version
	Icarus Verilog
$end
$timescale
	1s
$end
$scope module pipe_tb $end
$var wire 10 ! F [9:0] $end
$var parameter 32 " N $end
$var reg 10 # A [9:0] $end
$var reg 10 $ B [9:0] $end
$var reg 10 % C [9:0] $end
$var reg 10 & D [9:0] $end
$var reg 1 ' clk $end
$scope module UUT $end
$var wire 10 ( A [9:0] $end
$var wire 10 ) B [9:0] $end
$var wire 10 * C [9:0] $end
$var wire 10 + D [9:0] $end
$var wire 10 , F [9:0] $end
$var wire 1 ' clk $end
$var parameter 32 - N $end
$var reg 10 . L12_D [9:0] $end
$var reg 10 / L12_x1 [9:0] $end
$var reg 10 0 L12_x2 [9:0] $end
$var reg 10 1 L23_D [9:0] $end
$var reg 10 2 L23_x3 [9:0] $end
$var reg 10 3 L34_F [9:0] $end
$upscope $end
$upscope $end
$enddefinitions $end
$comment Show the parameter values. $end
$dumpall
b1010 -
b1010 "
$end
#0
$dumpvars
bx 3
bx 2
bx 1
bx 0
bx /
bx .
bx ,
bx +
bx *
bx )
bx (
0'
bx &
bx %
bx $
bx #
bx !
$end
#5
b11 &
b11 +
b110 %
b110 *
b1100 $
b1100 )
b1010 #
b1010 (
#10
b11 .
1'
#14
b11 0
b10110 /
#20
0'
#25
b101 %
b101 *
b1010 $
b1010 )
#30
b11 1
1'
#34
b11001 2
b10 0
b10100 /
#40
0'
#45
b100 &
b100 +
b1 %
b1 *
b1011 $
b1011 )
b10100 #
b10100 (
#50
b100 .
1'
#54
b1111111101 0
b11111 /
b10110 2
#56
b1001011 !
b1001011 ,
b1001011 3
#60
0'
#65
b10 &
b10 +
b1000 %
b1000 *
b1010 $
b1010 )
b1111 #
b1111 (
#70
b100 1
b10 .
1'
#74
b11100 2
b110 0
b11001 /
#76
b1000010 !
b1000010 ,
b1000010 3
#80
0'
#85
b0 &
b0 +
b101 %
b101 *
b1111 $
b1111 )
b1000 #
b1000 (
#90
b0 .
b10 1
1'
#94
b101 0
b10111 /
b11111 2
#96
b1110000 !
b1110000 ,
b1110000 3
#100
0'
#105
b11 &
b11 +
b10100 $
b10100 )
b1010 #
b1010 (
#110
b0 1
b11 .
1'
#114
b11100 2
b10 0
b11110 /
#116
b111110 !
b111110 ,
b111110 3
#120
0'
#125
b1 &
b1 +
b11110 %
b11110 *
b1010 $
b1010 )
#130
b1 .
b11 1
1'
#134
b11101 0
b10100 /
b100000 2
#136
b0 !
b0 ,
b0 3
#140
0'
#145
b100 &
b100 +
b10 %
b10 *
b1 $
b1 )
b11110 #
b11110 (
#150
b1 1
b100 .
1'
#154
b110001 2
b1111111110 0
b11111 /
#156
b1100000 !
b1100000 ,
b1100000 3
#160
0'
#170
b100 1
1'
#174
b11101 2
#176
b110001 !
b110001 ,
b110001 3
#180
0'
#190
1'
#196
b1110100 !
b1110100 ,
b1110100 3
