Day_012/majority16.v
module majority16 (Out, Data);
  input [0:15] Data;
  output Out;
  reg [0:4] count, i;

  assign Out = count > 5'b1000 ? 1 : 0;

  always @ (Data) begin
    count = 5'b0;
    for (i=0; i<= 15; i=i+1)
      if (Data[i] == 1) 
        count = count + 1;
  end
endmodule

Day_012/majority16_tb.v
module majority16_tb;
  reg [0:15] Data;
  wire Out;
  majority16 uut(Out, Data);
  initial begin
    $dumpfile("majority16.vcd");
    $dumpvars(0,majority16_tb);
    $monitor($time," Data=%b => Out=%b",Data,Out);
	  #5 Data=16'b1001000101111101;
	 #10 Data=16'b0101010101010101;
	 #15 Data=16'b1111001101010101;
	 #20 Data=16'b0010111111011110;
	 #25 Data=16'b1111111111111111;
	 #30 Data=16'b1111010110101111;
	 #35 Data=16'b1111100000110000;
	 #40 Data=16'b0;

  end
  endmodule

Day_012/majority16.vcd
$date
	Tue Sep  5 18:55:49 2023
$end
$version
	Icarus Verilog
$end
$timescale
	1s
$end
$scope module majority16_tb $end
$var wire 1 ! Out $end
$var reg 16 " Data [0:15] $end
$scope module uut $end
$var wire 16 # Data [0:15] $end
$var wire 1 ! Out $end
$var reg 5 $ count [0:4] $end
$var reg 5 % i [0:4] $end
$upscope $end
$upscope $end
$enddefinitions $end
$comment Show the parameter values. $end
$dumpall
$end
#0
$dumpvars
bx %
bx $
bx #
bx "
x!
$end
#5
1!
b10000 %
b1001 $
b1001000101111101 "
b1001000101111101 #
#15
0!
b10000 %
b1000 $
b101010101010101 "
b101010101010101 #
#30
1!
b10000 %
b1010 $
b1111001101010101 "
b1111001101010101 #
#50
b10000 %
b1011 $
b10111111011110 "
b10111111011110 #
#75
b10000 %
b10000 $
b1111111111111111 "
b1111111111111111 #
#105
b10000 %
b1100 $
b1111010110101111 "
b1111010110101111 #
#140
0!
b10000 %
b111 $
b1111100000110000 "
b1111100000110000 #
#180
b10000 %
b0 $
b0 "
b0 #
