Day_011/shift_reg.v
module shift_reg (clk, clr, A, E);
input clk,clr,A;
output reg E;
reg B,C,D;
always @(posedge clk or negedge clr) begin
    if (!clr) begin
        E<=D;
        D<=C;
        C<=B;
        B<=A;
    end
end
endmodule

Day_011/shift_reg_tb.v
module shift_reg_tb;
  reg clk;
  reg clr;
  reg A;
  wire E;

  shift_reg uut (.clk(clk), .clr(clr), .A(A), .E(E));

  always begin
    #5 clk = ~clk; 
  end

  initial begin
    $dumpfile("shift_reg.vcd");
    $dumpvars(0,shift_reg_tb);
    clk = 0;
    clr = 0;
    A = 0;

    clr = 1;
    #10 clr = 0;

    A = 1;
    #10 A = 0;
    #10 A = 1;
    #10 A = 0;
    #10 A = 1;
    #20
    $display("E = %b", E);
    $finish;
  end
endmodule

Day_011/shift_reg.vcd
$date
	Mon Sep  4 20:21:30 2023
$end
$version
	Icarus Verilog
$end
$timescale
	1s
$end
$scope module shift_reg_tb $end
$var wire 1 ! E $end
$var reg 1 " A $end
$var reg 1 # clk $end
$var reg 1 $ clr $end
$scope module uut $end
$var wire 1 " A $end
$var wire 1 # clk $end
$var wire 1 $ clr $end
$var reg 1 % B $end
$var reg 1 & C $end
$var reg 1 ' D $end
$var reg 1 ! E $end
$upscope $end
$upscope $end
$enddefinitions $end
$comment Show the parameter values. $end
$dumpall
$end
#0
$dumpvars
x'
x&
x%
1$
0#
0"
x!
$end
#5
1#
#10
1%
0#
1"
0$
#15
1&
1#
#20
0#
0"
#25
0%
1'
1#
#30
0#
1"
#35
1%
0&
1!
1#
#40
0#
0"
#45
0%
1&
0'
1#
#50
0#
1"
#55
1%
0&
1'
0!
1#
#60
0#
#65
1&
0'
1!
1#
