Day_009/updown_counter.v
module updown_counter(clk,d_in,rst,ld,mode,out);
    input clk,ld,rst,mode;
    input[7:0] d_in;
    output reg [7:0] out;
    always@(posedge clk)
        begin
            if (ld) 
                out <= d_in;
            else if (rst)
                out <= 0;
            else if (mode)
                out <= out+1;
            else
                out <= out-1;
        end
endmodule

Day_009/updown_counter_tb.v
module updown_counter_tb;

  reg clk;
  reg rst;
  reg ld;
  reg mode;
  reg [7:0] d_in;

  wire [7:0] out;

  updown_counter uut (
    .clk(clk),
    .rst(rst),
    .ld(ld),
    .mode(mode),
    .d_in(d_in),
    .out(out)
  );

  always begin
    #5 clk = ~clk; 
  end

  initial begin
    $dumpfile("updown_counter.vcd");
    $dumpvars(0,updown_counter_tb);
    $monitor($time," d_in=%b,rst=%b,ld=%b,mode=%b,out=%b", d_in,rst,ld,mode,out);
    clk = 0;
    rst = 0;
    ld = 0;
    mode = 0;
    d_in = 8'b00000000;

    rst = 1;
    #10 rst = 0;

    ld = 1;
    d_in = 8'b10101010; // Load a specific value
    #10;
    ld = 0; // Disable loading

    mode = 1; // Count up
    #20;
    mode = 0; // Count down
    #20;
    rst = 1;
    #20;
    
    $finish;
  end
endmodule

Day_009/updown_counter.vcd
$date
	Fri Sep  1 23:24:58 2023
$end
$version
	Icarus Verilog
$end
$timescale
	1s
$end
$scope module updown_counter_tb $end
$var wire 8 ! out [7:0] $end
$var reg 1 " clk $end
$var reg 8 # d_in [7:0] $end
$var reg 1 $ ld $end
$var reg 1 % mode $end
$var reg 1 & rst $end
$scope module uut $end
$var wire 1 " clk $end
$var wire 8 ' d_in [7:0] $end
$var wire 1 $ ld $end
$var wire 1 % mode $end
$var wire 1 & rst $end
$var reg 8 ( out [7:0] $end
$upscope $end
$upscope $end
$enddefinitions $end
$comment Show the parameter values. $end
$dumpall
$end
#0
$dumpvars
bx (
b0 '
1&
0%
0$
b0 #
0"
bx !
$end
#5
b0 !
b0 (
1"
#10
0"
b10101010 #
b10101010 '
1$
0&
#15
b10101010 !
b10101010 (
1"
#20
0"
1%
0$
#25
b10101011 !
b10101011 (
1"
#30
0"
#35
b10101100 !
b10101100 (
1"
#40
0"
0%
#45
b10101011 !
b10101011 (
1"
#50
0"
#55
b10101010 !
b10101010 (
1"
#60
0"
1&
#65
b0 !
b0 (
1"
