Day_013/lamp.v
module cyclic_lamp ( clk, out);
    input clk;
    output reg [2:0] out;
    parameter S0=0, S1=1, S2=2;
    parameter RED=3'b100, GREEN=3'b010, YELLOW=3'b001;
    reg [0:1] state;
    always @(posedge clk) 
        case (state)
        S0: state<=S1;
        S1: state<=S2;
        S2: state<=S0;
        default: state<=S0;
        endcase
    always @(state)
        case (state)
        S0: out<=RED;
        S1: out<=YELLOW;
        S2: out<=GREEN;
        default: out<=RED;
        endcase

endmodule

Day_013/cyclic_lamp_tb.v
module cyclic_lamp_tb;
    reg clk;
    wire [0:2] out;
    cyclic_lamp uut(.clk(clk), .out(out));
    always #5 clk = ~clk;
    initial begin
        clk=1'b0;
        #100 $finish;
    end
    initial begin
        $dumpfile("lamp.vcd");
        $dumpvars(0,cyclic_lamp_tb);
        $monitor($time," RGY=%b",out);
    end
endmodule

Day_013/lamp.vcd
$date
	Wed Sep  6 22:02:28 2023
$end
$version
	Icarus Verilog
$end
$timescale
	1s
$end
$scope module cyclic_lamp_tb $end
$var wire 3 ! out [0:2] $end
$var reg 1 " clk $end
$scope module uut $end
$var wire 1 " clk $end
$var parameter 3 # GREEN $end
$var parameter 3 $ RED $end
$var parameter 32 % S0 $end
$var parameter 32 & S1 $end
$var parameter 32 ' S2 $end
$var parameter 3 ( YELLOW $end
$var reg 3 ) out [2:0] $end
$var reg 2 * state [0:1] $end
$upscope $end
$upscope $end
$enddefinitions $end
$comment Show the parameter values. $end
$dumpall
b1 (
b10 '
b1 &
b0 %
b100 $
b10 #
$end
#0
$dumpvars
bx *
bx )
0"
bx !
$end
#5
b100 !
b100 )
b0 *
1"
#10
0"
#15
b1 !
b1 )
b1 *
1"
#20
0"
#25
b10 !
b10 )
b10 *
1"
#30
0"
#35
b100 !
b100 )
b0 *
1"
#40
0"
#45
b1 !
b1 )
b1 *
1"
#50
0"
#55
b10 !
b10 )
b10 *
1"
#60
0"
#65
b100 !
b100 )
b0 *
1"
#70
0"
#75
b1 !
b1 )
b1 *
1"
#80
0"
#85
b10 !
b10 )
b10 *
1"
#90
0"
#95
b100 !
b100 )
b0 *
1"
